ofcourse/.travis.yml
ofcourse/__init__.py
ofcourse/blueprints.py
ofcourse/participants.py
ofcourse/render.py
ofcourse/site.py
ofcourse/util.py
ofcourse/version.py
ofcourse/cli/__init__.py
ofcourse/cli/openshift_utils.py
ofcourse/cli/util.py
ofcourse/static/books/Open-Advice.pdf
ofcourse/static/css/bootstrap.min.css
ofcourse/static/css/material-wfont.min.css
ofcourse/static/css/material.min.css
ofcourse/static/css/pace.css
ofcourse/static/css/ripples.min.css
ofcourse/static/css/site.css
ofcourse/static/decks/hanginthere.jpg
ofcourse/static/fonts/LiberationSans-Regular-webfont.svg
ofcourse/static/fonts/LiberationSans-Regular-webfont.woff
ofcourse/static/fonts/Red Hat Liberation License.txt
ofcourse/static/fonts/glyphicons-halflings-regular.eot
ofcourse/static/fonts/glyphicons-halflings-regular.svg
ofcourse/static/fonts/glyphicons-halflings-regular.ttf
ofcourse/static/fonts/glyphicons-halflings-regular.woff
ofcourse/static/hw/addyourselftocoursewebsite.html
ofcourse/static/hw/createFASaccount.html
ofcourse/static/hw/creategithubaccount.html
ofcourse/static/hw/getyourfirstpullrequestaccepted.html
ofcourse/static/hw/issueapullrequest.html
ofcourse/static/img/favicon.ico
ofcourse/static/img/favicon.png
ofcourse/static/img/glyphicons-halflings-white.png
ofcourse/static/img/glyphicons-halflings.png
ofcourse/static/img/grid-baseline-20px.png
ofcourse/static/img/less-logo-large.png
ofcourse/static/img/responsive-illustrations.png
ofcourse/static/js/bootstrap.min.js
ofcourse/static/js/html5shiv.js
ofcourse/static/js/jquery.js
ofcourse/static/js/material.min.js
ofcourse/static/js/pace.min.js
ofcourse/static/js/ripples.min.js
ofcourse/tests/__init__.py
ofcourse/tests/__main__.py
ofcourse/tests/test_yaml.py
ofcourse/yamls/assignments.yaml
ofcourse/yamls/fake_student.yaml
ofcourse/yamls/oer.yaml
ofcourse/yamls/site.yaml
ofcourse-0.2.1.dist-info/DESCRIPTION.rst
ofcourse-0.2.1.dist-info/METADATA
ofcourse-0.2.1.dist-info/RECORD
ofcourse-0.2.1.dist-info/WHEEL
ofcourse-0.2.1.dist-info/entry_points.txt
ofcourse-0.2.1.dist-info/metadata.json
ofcourse-0.2.1.dist-info/pbr.json
ofcourse-0.2.1.dist-info/top_level.txt
ofcourse-templates/about.html
ofcourse-templates/blogs.html
ofcourse-templates/home.html
