Metadata-Version: 2.0
Name: ofcourse
Version: 0.2.1
Summary: Python courseware with Flask on OpenShift
Home-page: UNKNOWN
Author: Remy DeCausemaker
Author-email: remyd@civx.us
License: ASL2.0
Keywords: courseware
Requires-Dist: Click (>=3.1)
Requires-Dist: Flask (>=0.10.1)
Requires-Dist: Flask-Mako (>=0.3)
Requires-Dist: Frozen-Flask (>=0.11)
Requires-Dist: Mako (>=1.0.0)
Requires-Dist: PyYAML (>=3.11)
Requires-Dist: dulwich (>=0.9.0)
Requires-Dist: feedparser (>=5.1.3)
Requires-Dist: oshift (>=0.2.2)
Requires-Dist: six (>=1.7.3)
Requires-Dist: tornado (>=4.0.1)
Requires-Dist: validator.py (>=1.2.0)
